onsite/__init__.py
onsite/ascore/__init__.py
onsite/ascore/ascore.py
onsite/ascore/cli.py
onsite/lucxor/__init__.py
onsite/lucxor/cli.py
onsite/lucxor/config.py
onsite/lucxor/constants.py
onsite/lucxor/core.py
onsite/lucxor/flr.py
onsite/lucxor/globals.py
onsite/lucxor/models.py
onsite/lucxor/parallel.py
onsite/lucxor/peak.py
onsite/lucxor/peptide.py
onsite/lucxor/psm.py
onsite/lucxor/spectrum.py
onsite/onsitec.py
onsite/phosphors/__init__.py
onsite/phosphors/cli.py
onsite/phosphors/phosphors.py
pyonsite-0.0.2.dist-info/METADATA
pyonsite-0.0.2.dist-info/WHEEL
pyonsite-0.0.2.dist-info/entry_points.txt
pyonsite-0.0.2.dist-info/licenses/LICENSE
pyonsite-0.0.2.dist-info/RECORD
