Metadata-Version: 2.4
Name: pyonsite
Version: 0.0.2
Summary: onsite: mass spectrometry post-translational localization tool
License-Expression: MIT
License-File: LICENSE
Keywords: mass-spectrometry,proteomics,phosphorylation,ptm,ascore,phosphors
Author: BigBio Stack
Requires-Python: >=3.11
Classifier: Development Status :: 3 - Alpha
Classifier: Intended Audience :: Science/Research
Classifier: License :: OSI Approved :: MIT License
Classifier: Operating System :: OS Independent
Classifier: Programming Language :: Python :: 3
Classifier: Programming Language :: Python :: 3.11
Classifier: Programming Language :: Python :: 3.12
Classifier: Topic :: Scientific/Engineering :: Bio-Informatics
Classifier: Topic :: Scientific/Engineering :: Chemistry
Requires-Dist: click (>=8.0.0)
Requires-Dist: numpy (>=2.3.2)
Requires-Dist: pyopenms (==3.4.0)
Requires-Dist: scipy (>=1.16.1)
Project-URL: Documentation, https://github.com/bigbio/onsite
Project-URL: Homepage, https://github.com/bigbio/onsite
Project-URL: Repository, https://github.com/bigbio/onsite
